polymarket_pandas/polymarket_pandas.py
polymarket_pandas-0.1.0.dist-info/licenses/LICENSE
polymarket_pandas-0.1.0.dist-info/METADATA
polymarket_pandas-0.1.0.dist-info/WHEEL
polymarket_pandas-0.1.0.dist-info/RECORD
