Metadata-Version: 2.4
Name: polymarket-pandas
Version: 0.1.0
Summary: Pandas API client to Polymarket
License-Expression: Apache-2.0
License-File: LICENSE
Author: Sigma Quantiphi
Author-email: contact@sqphi.com
Requires-Python: >=3.11
Classifier: Programming Language :: Python :: 3
Classifier: Programming Language :: Python :: 3.11
Classifier: Programming Language :: Python :: 3.12
Classifier: Programming Language :: Python :: 3.13
Classifier: Programming Language :: Python :: 3.14
Requires-Dist: cachetools (>=6.0.0,<7.0.0)
Requires-Dist: httpx (>=0.28.1,<1.0.0)
Requires-Dist: pandas[computation,output-formatting,performance] (>=2.2.3,<3.0.0)
Requires-Dist: pandera (>=0.22.1,<1.0.0)
Project-URL: Documentation, https://github.com/sigma-quantiphi/polymarket-pandas
Project-URL: Homepage, https://github.com/sigma-quantiphi/polymarket-pandas
Project-URL: Repository, https://github.com/sigma-quantiphi/polymarket-pandas
